{
    "canvas": "https://www.dl.ndl.go.jp/api/iiif/3437687/canvas/171",
    "label": [
        "たわなむあんなるあたらものをといふなるをきくもゆゝしくいかさまにして宮",
        "こにいてたてまつりてちゝおとゝにしらせたてまつらむいときなきほとをいと",
        "らうたしと思きこえ給へりしかはさりともおろかには思すてきこえ給はしなと",
        "いひなけくほと仏神に願をたてゝなむ念しけるむすめともゝおのこともゝとこ",
        "ろにつけたるよすかともいてきてすみつきにたり心のうちにこそいそき思へと",
        "京の事はいやとをさかるやうにへたゝりゆくものおほしゝるまゝによをいとう",
        "きものにおほして年三なとし給廿はかりになり給まゝにおひとゝのほりていと",
        "あたらしくめてたしこのすむ所はひせむの国とそいひけるそのわたりにもいさ",
        "ゝかよしある人はまつこのせうにのむまこのありさまをきゝつたへて猶たえす",
        "をとつれくるもいといみしうみゝかしかましきまてなむ大夫監とてひこのくに",
        "ゝそうひろくてかしこにつけてはおほえありいきをひいかめしきつはものあり",
        "けりむくつけき心の中にいさゝかすきたる心ましりてかたちある女をあつめて",
        "みむと思けるこのひめ君を聞つけていみしきかたわありとも我はみかくしても",
        "たらむといとねむころにいひかゝるをいとむくつけくおもひていかてかゝる事"
    ],
    "manifest": "https://www.dl.ndl.go.jp/api/iiif/3437687/manifest.json",
    "next": "0724",
    "page": 723,
    "prev": "0722",
    "related": {
        "kyoto_rb00007030": [
            {
                "attribution": "京都大学",
                "canvas": "https://rmda.kulib.kyoto-u.ac.jp/iiif/RB00007030/page539738",
                "image": "https://rmda.kulib.kyoto-u.ac.jp/iiif/RB00007030/20/RB00007030_00890_0.ptif/full/200,/0/default.jpg",
                "manifest": "https://raw.githubusercontent.com/nakamura196/genji_curation/master/docs/iiif/kyoto02/22.json",
                "name": "中院文庫本",
                "page": 8,
                "type": "コマ",
                "work": "玉鬘"
            },
            {
                "attribution": "京都大学",
                "canvas": "https://rmda.kulib.kyoto-u.ac.jp/iiif/RB00007030/page539739",
                "image": "https://rmda.kulib.kyoto-u.ac.jp/iiif/RB00007030/20/RB00007030_00891_0.ptif/full/200,/0/default.jpg",
                "manifest": "https://raw.githubusercontent.com/nakamura196/genji_curation/master/docs/iiif/kyoto02/22.json",
                "name": "中院文庫本",
                "page": 9,
                "type": "コマ",
                "work": "玉鬘"
            }
        ],
        "kyushu_2324-411193": [
            {
                "attribution": "九州大学",
                "canvas": "https://catalog.lib.kyushu-u.ac.jp/image/411222/canvas/p8",
                "curation": 1,
                "image": "https://catalog.lib.kyushu-u.ac.jp/image/iiif/820/411222/370113.tiff/full/200,/0/default.jpg",
                "manifest": "https://genji.dl.itc.u-tokyo.ac.jp/data/iiif/org/%E4%B9%9D%E5%A4%A7%E6%9C%AC%EF%BC%88%E5%8F%A4%E6%B4%BB%E5%AD%97%E7%89%88%EF%BC%89/22/manifest.json",
                "name": "九州大学文学部 所蔵 源氏物語 古活字版",
                "page": 8,
                "type": "コマ",
                "vol": 22,
                "work": "九大本（古活字版）"
            },
            {
                "attribution": "九州大学",
                "canvas": "https://catalog.lib.kyushu-u.ac.jp/image/411222/canvas/p9",
                "curation": 1,
                "image": "https://catalog.lib.kyushu-u.ac.jp/image/iiif/820/411222/370114.tiff/full/200,/0/default.jpg",
                "line": "04",
                "manifest": "https://genji.dl.itc.u-tokyo.ac.jp/data/iiif/org/%E4%B9%9D%E5%A4%A7%E6%9C%AC%EF%BC%88%E5%8F%A4%E6%B4%BB%E5%AD%97%E7%89%88%EF%BC%89/22/manifest.json",
                "name": "九州大学文学部 所蔵 源氏物語 古活字版",
                "page": 9,
                "type": "コマ",
                "vol": 22,
                "work": "九大本（古活字版）"
            }
        ],
        "kyushu_2324-411265": [
            {
                "attribution": "九州大学",
                "canvas": "https://catalog.lib.kyushu-u.ac.jp/image/411286/canvas/p10",
                "curation": 1,
                "image": "https://catalog.lib.kyushu-u.ac.jp/image/iiif/820/411286/373971.tiff/full/200,/0/default.jpg",
                "line": "05",
                "manifest": "https://genji.dl.itc.u-tokyo.ac.jp/data/iiif/org/%E4%B9%9D%E5%A4%A7%E6%9C%AC%EF%BC%88%E7%84%A1%E8%B7%8B%E7%84%A1%E5%88%8A%E8%A8%98%E6%95%B4%E7%89%88%E6%9C%AC%EF%BC%89/22/manifest.json",
                "name": "個人蔵 源氏物語 無跋無刊記整版本",
                "page": 10,
                "type": "コマ",
                "vol": 22,
                "work": "九大本（無跋無刊記整版本）"
            },
            {
                "attribution": "九州大学",
                "canvas": "https://catalog.lib.kyushu-u.ac.jp/image/411286/canvas/p11",
                "curation": 1,
                "image": "https://catalog.lib.kyushu-u.ac.jp/image/iiif/820/411286/373972.tiff/full/200,/0/default.jpg",
                "manifest": "https://genji.dl.itc.u-tokyo.ac.jp/data/iiif/org/%E4%B9%9D%E5%A4%A7%E6%9C%AC%EF%BC%88%E7%84%A1%E8%B7%8B%E7%84%A1%E5%88%8A%E8%A8%98%E6%95%B4%E7%89%88%E6%9C%AC%EF%BC%89/22/manifest.json",
                "name": "個人蔵 源氏物語 無跋無刊記整版本",
                "page": 11,
                "type": "コマ",
                "vol": 22,
                "work": "九大本（無跋無刊記整版本）"
            }
        ],
        "ndl_1288440": [
            {
                "attribution": "国立国会図書館",
                "canvas": "https://www.dl.ndl.go.jp/api/iiif/1288297/canvas/7",
                "curation": 1,
                "image": "https://www.dl.ndl.go.jp/api/iiif/1288297/F0000007/full/full/0/default.jpg",
                "line": "14",
                "manifest": "https://www.dl.ndl.go.jp/api/iiif/1288297/manifest.json",
                "name": "慶長古活字版（国立国会図書館所蔵）",
                "page": 7,
                "type": "コマ",
                "vol": 22,
                "work": "〔源氏物語〕. 玉かつら"
            },
            {
                "attribution": "国立国会図書館",
                "canvas": "https://www.dl.ndl.go.jp/api/iiif/1288297/canvas/8",
                "curation": 1,
                "image": "https://www.dl.ndl.go.jp/api/iiif/1288297/F0000008/full/full/0/default.jpg",
                "manifest": "https://www.dl.ndl.go.jp/api/iiif/1288297/manifest.json",
                "name": "慶長古活字版（国立国会図書館所蔵）",
                "page": 8,
                "type": "コマ",
                "vol": 22,
                "work": "〔源氏物語〕. 玉かつら"
            }
        ],
        "ndl_2585098": [
            {
                "attribution": "国立国会図書館",
                "canvas": "https://www.dl.ndl.go.jp/api/iiif/2585119/canvas/14",
                "curation": 1,
                "image": "https://www.dl.ndl.go.jp/api/iiif/2585119/F0000014/full/full/0/default.jpg",
                "line": "13",
                "manifest": "https://www.dl.ndl.go.jp/api/iiif/2585119/manifest.json",
                "name": "東久邇宮家旧蔵（国立国会図書館所蔵）",
                "page": 14,
                "type": "コマ",
                "vol": 22,
                "work": "[源氏物語]. [22]"
            },
            {
                "attribution": "国立国会図書館",
                "canvas": "https://www.dl.ndl.go.jp/api/iiif/2585119/canvas/15",
                "curation": 1,
                "image": "https://www.dl.ndl.go.jp/api/iiif/2585119/F0000015/full/full/0/default.jpg",
                "manifest": "https://www.dl.ndl.go.jp/api/iiif/2585119/manifest.json",
                "name": "東久邇宮家旧蔵（国立国会図書館所蔵）",
                "page": 15,
                "type": "コマ",
                "vol": 22,
                "work": "[源氏物語]. [22]"
            }
        ],
        "ndl_2610583": [
            {
                "attribution": "国会図書館",
                "canvas": "https://www.dl.ndl.go.jp/api/iiif/3010894/canvas/6",
                "image": "https://www.dl.ndl.go.jp/api/iiif/3010894/F0000006/full/full/0/default.jpg",
                "manifest": "https://raw.githubusercontent.com/nakamura196/genji_curation/master/docs/iiif/ndl04/22.json",
                "name": "元和9年古活字版",
                "page": 6,
                "type": "コマ",
                "work": "[源氏物語] 54巻. [22]"
            },
            {
                "attribution": "国会図書館",
                "canvas": "https://www.dl.ndl.go.jp/api/iiif/3010894/canvas/7",
                "image": "https://www.dl.ndl.go.jp/api/iiif/3010894/F0000007/full/full/0/default.jpg",
                "manifest": "https://raw.githubusercontent.com/nakamura196/genji_curation/master/docs/iiif/ndl04/22.json",
                "name": "元和9年古活字版",
                "page": 7,
                "type": "コマ",
                "work": "[源氏物語] 54巻. [22]"
            }
        ],
        "ndl_2610937": [
            {
                "attribution": "国会図書館",
                "canvas": "https://www.dl.ndl.go.jp/api/iiif/2585119/canvas/14",
                "image": "https://www.dl.ndl.go.jp/api/iiif/2585119/F0000014/full/full/0/default.jpg",
                "manifest": "https://raw.githubusercontent.com/nakamura196/genji_curation/master/docs/iiif/ndl03/22.json",
                "name": "近世前期写本",
                "page": 14,
                "type": "コマ",
                "work": "[源氏物語]. [22]"
            },
            {
                "attribution": "国会図書館",
                "canvas": "https://www.dl.ndl.go.jp/api/iiif/2585119/canvas/15",
                "image": "https://www.dl.ndl.go.jp/api/iiif/2585119/F0000015/full/full/0/default.jpg",
                "manifest": "https://raw.githubusercontent.com/nakamura196/genji_curation/master/docs/iiif/ndl03/22.json",
                "name": "近世前期写本",
                "page": 15,
                "type": "コマ",
                "work": "[源氏物語]. [22]"
            }
        ],
        "ndl_8943312": [
            {
                "attribution": "国会図書館",
                "canvas": "https://www.dl.ndl.go.jp/api/iiif/8943196/canvas/33",
                "image": "https://www.dl.ndl.go.jp/api/iiif/8943196/F0000033/full/full/0/default.jpg",
                "manifest": "https://raw.githubusercontent.com/nakamura196/genji_curation/master/docs/iiif/ndl02/22.json",
                "name": "伝嵯峨本",
                "page": 33,
                "type": "コマ",
                "work": "[源氏物語] 54巻. 22"
            },
            {
                "attribution": "国会図書館",
                "canvas": "https://www.dl.ndl.go.jp/api/iiif/8943196/canvas/34",
                "image": "https://www.dl.ndl.go.jp/api/iiif/8943196/F0000034/full/full/0/default.jpg",
                "manifest": "https://raw.githubusercontent.com/nakamura196/genji_curation/master/docs/iiif/ndl02/22.json",
                "name": "伝嵯峨本",
                "page": 34,
                "type": "コマ",
                "work": "[源氏物語] 54巻. 22"
            }
        ],
        "nijl_100050894": [
            {
                "attribution": "鹿児島大学",
                "canvas": "https://kotenseki.nijl.ac.jp/biblio/100050894/canvas/818",
                "curation": 1,
                "image": "https://kotenseki.nijl.ac.jp/api/iiif/100050894/v4/0091/0091-027802/0091-027802-0817.tif/full/200,/0/default.jpg",
                "manifest": "https://kotenseki.nijl.ac.jp/biblio/100050894/manifest",
                "name": "玉里文庫（鹿児島大学所蔵）",
                "page": 818,
                "type": "コマ",
                "vol": 22,
                "work": "源氏物語"
            },
            {
                "attribution": "鹿児島大学",
                "canvas": "https://kotenseki.nijl.ac.jp/biblio/100050894/canvas/819",
                "curation": 1,
                "image": "https://kotenseki.nijl.ac.jp/api/iiif/100050894/v4/0091/0091-027802/0091-027802-0818.tif/full/200,/0/default.jpg",
                "line": "03",
                "manifest": "https://kotenseki.nijl.ac.jp/biblio/100050894/manifest",
                "name": "玉里文庫（鹿児島大学所蔵）",
                "page": 819,
                "type": "コマ",
                "vol": 22,
                "work": "源氏物語"
            }
        ],
        "nijl_100130618": [
            {
                "attribution": "宮内庁書陵部",
                "canvas": "https://kotenseki.nijl.ac.jp/biblio/100130618/canvas/880",
                "curation": 1,
                "image": "https://kotenseki.nijl.ac.jp/api/iiif/100130618/v4/0020/0020-44501/0020-44501-0879.tif/full/200,/0/default.jpg",
                "manifest": "https://kotenseki.nijl.ac.jp/biblio/100130618/manifest",
                "name": "宮内庁書陵部所蔵本",
                "page": 880,
                "type": "コマ",
                "vol": 22,
                "work": "源氏物語"
            },
            {
                "attribution": "宮内庁書陵部",
                "canvas": "https://kotenseki.nijl.ac.jp/biblio/100130618/canvas/881",
                "curation": 1,
                "image": "https://kotenseki.nijl.ac.jp/api/iiif/100130618/v4/0020/0020-44501/0020-44501-0880.tif/full/200,/0/default.jpg",
                "line": "09",
                "manifest": "https://kotenseki.nijl.ac.jp/biblio/100130618/manifest",
                "name": "宮内庁書陵部所蔵本",
                "page": 881,
                "type": "コマ",
                "vol": 22,
                "work": "源氏物語"
            }
        ],
        "nijl_100153620": [
            {
                "attribution": "京都大学",
                "canvas": "https://kotenseki.nijl.ac.jp/biblio/100153620/canvas/986",
                "image": "https://kotenseki.nijl.ac.jp/api/iiif/100153620/v4/0327/0327-000608/0327-000608-0985.tif/full/200,/0/default.jpg",
                "manifest": "https://raw.githubusercontent.com/nakamura196/genji_curation/master/docs/iiif/kyoto01/22.json",
                "name": "平松家本",
                "page": 9,
                "type": "コマ",
                "work": "玉鬘"
            },
            {
                "attribution": "京都大学",
                "canvas": "https://kotenseki.nijl.ac.jp/biblio/100153620/canvas/987",
                "image": "https://kotenseki.nijl.ac.jp/api/iiif/100153620/v4/0327/0327-000608/0327-000608-0986.tif/full/200,/0/default.jpg",
                "manifest": "https://raw.githubusercontent.com/nakamura196/genji_curation/master/docs/iiif/kyoto01/22.json",
                "name": "平松家本",
                "page": 10,
                "type": "コマ",
                "work": "玉鬘"
            }
        ],
        "nijl_100153621": [
            {
                "attribution": "京都大学",
                "canvas": "https://kotenseki.nijl.ac.jp/biblio/100153621/canvas/996",
                "curation": 1,
                "image": "https://kotenseki.nijl.ac.jp/api/iiif/100153621/v4/0327/0327-001102/0327-001102-0995.tif/full/200,/0/default.jpg",
                "manifest": "https://kotenseki.nijl.ac.jp/biblio/100153621/manifest",
                "name": "平松家本 11-2 （京都大学所蔵）",
                "page": 996,
                "type": "コマ",
                "vol": 22,
                "work": "源氏物語"
            },
            {
                "attribution": "京都大学",
                "canvas": "https://kotenseki.nijl.ac.jp/biblio/100153621/canvas/997",
                "curation": 1,
                "image": "https://kotenseki.nijl.ac.jp/api/iiif/100153621/v4/0327/0327-001102/0327-001102-0996.tif/full/200,/0/default.jpg",
                "line": "05",
                "manifest": "https://kotenseki.nijl.ac.jp/biblio/100153621/manifest",
                "name": "平松家本 11-2 （京都大学所蔵）",
                "page": 997,
                "type": "コマ",
                "vol": 22,
                "work": "源氏物語"
            }
        ],
        "nijl_100182342": [
            {
                "attribution": "国文学研究資料館",
                "canvas": "https://kotenseki.nijl.ac.jp/biblio/100182342/canvas/838",
                "curation": 1,
                "image": "https://kotenseki.nijl.ac.jp/api/iiif/100182342/v4/0358/0358-00501/0358-00501-0837.tif/full/200,/0/default.jpg",
                "manifest": "https://kotenseki.nijl.ac.jp/biblio/100182342/manifest",
                "name": "肥前松平文庫",
                "page": 838,
                "type": "コマ",
                "vol": 22,
                "work": "源氏物語"
            },
            {
                "attribution": "国文学研究資料館",
                "canvas": "https://kotenseki.nijl.ac.jp/biblio/100182342/canvas/839",
                "curation": 1,
                "image": "https://kotenseki.nijl.ac.jp/api/iiif/100182342/v4/0358/0358-00501/0358-00501-0838.tif/full/200,/0/default.jpg",
                "line": "11",
                "manifest": "https://kotenseki.nijl.ac.jp/biblio/100182342/manifest",
                "name": "肥前松平文庫",
                "page": 839,
                "type": "コマ",
                "vol": 22,
                "work": "源氏物語"
            }
        ],
        "nijl_100190213": [
            {
                "attribution": "国文学研究資料館",
                "canvas": "https://kotenseki.nijl.ac.jp/biblio/100190213/canvas/871",
                "curation": 1,
                "image": "https://kotenseki.nijl.ac.jp/api/iiif/100190213/v4/0020/0020-60301/0020-60301-0870.tif/full/200,/0/default.jpg",
                "manifest": "https://kotenseki.nijl.ac.jp/biblio/100190213/manifest",
                "name": "河内本（宮内庁書陵部）",
                "page": 871,
                "type": "コマ",
                "vol": 22,
                "work": "源氏物語"
            },
            {
                "attribution": "国文学研究資料館",
                "canvas": "https://kotenseki.nijl.ac.jp/biblio/100190213/canvas/872",
                "curation": 1,
                "image": "https://kotenseki.nijl.ac.jp/api/iiif/100190213/v4/0020/0020-60301/0020-60301-0871.tif/full/200,/0/default.jpg",
                "line": "05",
                "manifest": "https://kotenseki.nijl.ac.jp/biblio/100190213/manifest",
                "name": "河内本（宮内庁書陵部）",
                "page": 872,
                "type": "コマ",
                "vol": 22,
                "work": "源氏物語"
            }
        ],
        "nijl_100232449": [
            {
                "attribution": "国文学研究資料館",
                "canvas": "https://kotenseki.nijl.ac.jp/biblio/100232449/canvas/756",
                "curation": 1,
                "image": "https://kotenseki.nijl.ac.jp/api/iiif/100232449/v4/0397/0397-001901/0397-001901-0185.tif/full/200,/0/default.jpg",
                "line": "18",
                "manifest": "https://kotenseki.nijl.ac.jp/biblio/100232449/manifest",
                "name": "相愛大学図書館 所蔵本 1",
                "page": 756,
                "type": "コマ",
                "vol": 22,
                "work": "源氏物語"
            },
            {
                "attribution": "国文学研究資料館",
                "canvas": "https://kotenseki.nijl.ac.jp/biblio/100232449/canvas/757",
                "curation": 1,
                "image": "https://kotenseki.nijl.ac.jp/api/iiif/100232449/v4/0397/0397-001901/0397-001901-0186.tif/full/200,/0/default.jpg",
                "manifest": "https://kotenseki.nijl.ac.jp/biblio/100232449/manifest",
                "name": "相愛大学図書館 所蔵本 1",
                "page": 757,
                "type": "コマ",
                "vol": 22,
                "work": "源氏物語"
            }
        ],
        "nijl_100232477": [
            {
                "attribution": "国文学研究資料館",
                "canvas": "https://kotenseki.nijl.ac.jp/biblio/100232477/canvas/887",
                "curation": 1,
                "image": "https://kotenseki.nijl.ac.jp/api/iiif/100232477/v4/0397/0397-002801/0397-002801-0294.tif/full/200,/0/default.jpg",
                "manifest": "https://kotenseki.nijl.ac.jp/biblio/100232477/manifest",
                "name": "相愛大学図書館 所蔵本 2",
                "page": 887,
                "type": "コマ",
                "vol": 22,
                "work": "源氏物語"
            },
            {
                "attribution": "国文学研究資料館",
                "canvas": "https://kotenseki.nijl.ac.jp/biblio/100232477/canvas/888",
                "curation": 1,
                "image": "https://kotenseki.nijl.ac.jp/api/iiif/100232477/v4/0397/0397-002801/0397-002801-0295.tif/full/200,/0/default.jpg",
                "line": "19",
                "manifest": "https://kotenseki.nijl.ac.jp/biblio/100232477/manifest",
                "name": "相愛大学図書館 所蔵本 2",
                "page": 888,
                "type": "コマ",
                "vol": 22,
                "work": "源氏物語"
            }
        ],
        "nijl_100232530": [
            {
                "attribution": "国文学研究資料館",
                "canvas": "https://kotenseki.nijl.ac.jp/biblio/100232535/canvas/972",
                "curation": 1,
                "image": "https://kotenseki.nijl.ac.jp/api/iiif/100232535/v4/0397/0397-005001/0397-005001-0397.tif/full/200,/0/default.jpg",
                "manifest": "https://kotenseki.nijl.ac.jp/biblio/100232535/manifest",
                "name": "相愛大学図書館 所蔵本 4",
                "page": 972,
                "type": "コマ",
                "vol": 22,
                "work": "源氏物語"
            },
            {
                "attribution": "国文学研究資料館",
                "canvas": "https://kotenseki.nijl.ac.jp/biblio/100232535/canvas/973",
                "curation": 1,
                "image": "https://kotenseki.nijl.ac.jp/api/iiif/100232535/v4/0397/0397-005001/0397-005001-0398.tif/full/200,/0/default.jpg",
                "line": "03",
                "manifest": "https://kotenseki.nijl.ac.jp/biblio/100232535/manifest",
                "name": "相愛大学図書館 所蔵本 4",
                "page": 973,
                "type": "コマ",
                "vol": 22,
                "work": "源氏物語"
            }
        ],
        "nijl_100232535": [
            {
                "attribution": "国文学研究資料館",
                "canvas": "https://kotenseki.nijl.ac.jp/biblio/100232535/canvas/972",
                "curation": 1,
                "image": "https://kotenseki.nijl.ac.jp/api/iiif/100232535/v4/0397/0397-005001/0397-005001-0397.tif/full/200,/0/default.jpg",
                "manifest": "https://kotenseki.nijl.ac.jp/biblio/100232535/manifest",
                "name": "相愛大学図書館 所蔵本 4",
                "page": 972,
                "type": "コマ",
                "vol": 22,
                "work": "源氏物語"
            },
            {
                "attribution": "国文学研究資料館",
                "canvas": "https://kotenseki.nijl.ac.jp/biblio/100232535/canvas/973",
                "curation": 1,
                "image": "https://kotenseki.nijl.ac.jp/api/iiif/100232535/v4/0397/0397-005001/0397-005001-0398.tif/full/200,/0/default.jpg",
                "line": "03",
                "manifest": "https://kotenseki.nijl.ac.jp/biblio/100232535/manifest",
                "name": "相愛大学図書館 所蔵本 4",
                "page": 973,
                "type": "コマ",
                "vol": 22,
                "work": "源氏物語"
            }
        ],
        "nijl_100235297": [
            {
                "attribution": "国文学研究資料館",
                "canvas": "https://kotenseki.nijl.ac.jp/biblio/100135297/canvas/882",
                "curation": 1,
                "image": "https://kotenseki.nijl.ac.jp/api/iiif/100135297/v4/0257/0257-030702/0257-030702-0881.tif/full/200,/0/default.jpg",
                "manifest": "https://kotenseki.nijl.ac.jp/biblio/100135297/manifest",
                "name": "大和文華館所蔵本",
                "page": 882,
                "type": "コマ",
                "vol": 22,
                "work": "源氏物語"
            },
            {
                "attribution": "国文学研究資料館",
                "canvas": "https://kotenseki.nijl.ac.jp/biblio/100135297/canvas/883",
                "curation": 1,
                "image": "https://kotenseki.nijl.ac.jp/api/iiif/100135297/v4/0257/0257-030702/0257-030702-0882.tif/full/200,/0/default.jpg",
                "line": "09",
                "manifest": "https://kotenseki.nijl.ac.jp/biblio/100135297/manifest",
                "name": "大和文華館所蔵本",
                "page": 883,
                "type": "コマ",
                "vol": 22,
                "work": "源氏物語"
            }
        ],
        "nijl_100250108": [
            {
                "attribution": "国文学研究資料館",
                "canvas": "https://kotenseki.nijl.ac.jp/biblio/100250108/canvas/744",
                "curation": 1,
                "image": "https://kotenseki.nijl.ac.jp/api/iiif/100250108/v4/UWJM/UWJM-00060/UWJM-00060-0743.tif/full/200,/0/default.jpg",
                "line": "21",
                "manifest": "https://kotenseki.nijl.ac.jp/biblio/100250108/manifest",
                "name": "宇和島伊達文化保存会 所蔵本",
                "page": 744,
                "type": "コマ",
                "vol": 22,
                "work": "源氏物語"
            },
            {
                "attribution": "国文学研究資料館",
                "canvas": "https://kotenseki.nijl.ac.jp/biblio/100250108/canvas/745",
                "curation": 1,
                "image": "https://kotenseki.nijl.ac.jp/api/iiif/100250108/v4/UWJM/UWJM-00060/UWJM-00060-0744.tif/full/200,/0/default.jpg",
                "manifest": "https://kotenseki.nijl.ac.jp/biblio/100250108/manifest",
                "name": "宇和島伊達文化保存会 所蔵本",
                "page": 745,
                "type": "コマ",
                "vol": 22,
                "work": "源氏物語"
            }
        ],
        "nijl_100260423": [
            {
                "attribution": "お茶の水女子大学",
                "canvas": "https://kotenseki.nijl.ac.jp/biblio/100260423/canvas/880",
                "curation": 1,
                "image": "https://kotenseki.nijl.ac.jp/api/iiif/100260423/v4/OCHA/OCHA-00923/OCHA-00923-00879.tif/full/200,/0/default.jpg",
                "line": "13",
                "manifest": "https://kotenseki.nijl.ac.jp/biblio/100260423/manifest",
                "name": "お茶の水女子大学所蔵本",
                "page": 880,
                "type": "コマ",
                "vol": 22,
                "work": "源氏物語"
            },
            {
                "attribution": "お茶の水女子大学",
                "canvas": "https://kotenseki.nijl.ac.jp/biblio/100260423/canvas/881",
                "curation": 1,
                "image": "https://kotenseki.nijl.ac.jp/api/iiif/100260423/v4/OCHA/OCHA-00923/OCHA-00923-00880.tif/full/200,/0/default.jpg",
                "manifest": "https://kotenseki.nijl.ac.jp/biblio/100260423/manifest",
                "name": "お茶の水女子大学所蔵本",
                "page": 881,
                "type": "コマ",
                "vol": 22,
                "work": "源氏物語"
            }
        ],
        "nijl_100266039": [
            {
                "attribution": "国文学研究資料館",
                "canvas": "https://kotenseki.nijl.ac.jp/biblio/100266039/canvas/805",
                "curation": 1,
                "image": "https://kotenseki.nijl.ac.jp/api/iiif/100266039/v4/JWUL/JWUL-00001/JWUL-00001-00804.tif/full/200,/0/default.jpg",
                "line": "14",
                "manifest": "https://kotenseki.nijl.ac.jp/biblio/100266039/manifest",
                "name": "実践女子大学・実践女子大学短期大学部図書館 所蔵本",
                "page": 805,
                "type": "コマ",
                "vol": 22,
                "work": "源氏物語"
            },
            {
                "attribution": "国文学研究資料館",
                "canvas": "https://kotenseki.nijl.ac.jp/biblio/100266039/canvas/806",
                "curation": 1,
                "image": "https://kotenseki.nijl.ac.jp/api/iiif/100266039/v4/JWUL/JWUL-00001/JWUL-00001-00805.tif/full/200,/0/default.jpg",
                "manifest": "https://kotenseki.nijl.ac.jp/biblio/100266039/manifest",
                "name": "実践女子大学・実践女子大学短期大学部図書館 所蔵本",
                "page": 806,
                "type": "コマ",
                "vol": 22,
                "work": "源氏物語"
            }
        ],
        "nijl_100292059": [
            {
                "attribution": "国文学研究資料館",
                "canvas": "https://kotenseki.nijl.ac.jp/biblio/100292059/canvas/688",
                "curation": 1,
                "image": "https://kotenseki.nijl.ac.jp/api/iiif/100292059/v4/HMGC/HMGC-00060/HMGC-00060-0687.tif/full/200,/0/default.jpg",
                "line": "15",
                "manifest": "https://kotenseki.nijl.ac.jp/biblio/100292059/manifest",
                "name": "浜口博章",
                "page": 688,
                "type": "コマ",
                "vol": 22,
                "work": "源氏物語"
            },
            {
                "attribution": "国文学研究資料館",
                "canvas": "https://kotenseki.nijl.ac.jp/biblio/100292059/canvas/689",
                "curation": 1,
                "image": "https://kotenseki.nijl.ac.jp/api/iiif/100292059/v4/HMGC/HMGC-00060/HMGC-00060-0688.tif/full/200,/0/default.jpg",
                "manifest": "https://kotenseki.nijl.ac.jp/biblio/100292059/manifest",
                "name": "浜口博章",
                "page": 689,
                "type": "コマ",
                "vol": 22,
                "work": "源氏物語"
            }
        ],
        "nijl_200000993": [
            {
                "attribution": "国文学研究資料館",
                "canvas": "https://kotenseki.nijl.ac.jp/biblio/200000993/canvas/779",
                "curation": 1,
                "image": "https://kotenseki.nijl.ac.jp/api/iiif/200000993/v4/image/110_0089/00000001/00000264.tif/full/200,/0/default.jpg",
                "manifest": "https://kotenseki.nijl.ac.jp/biblio/200000993/manifest",
                "name": "200000993 国文学研究資料館所蔵本",
                "page": 779,
                "type": "コマ",
                "vol": 22,
                "work": "源氏物語"
            },
            {
                "attribution": "国文学研究資料館",
                "canvas": "https://kotenseki.nijl.ac.jp/biblio/200000993/canvas/780",
                "curation": 1,
                "image": "https://kotenseki.nijl.ac.jp/api/iiif/200000993/v4/image/110_0089/00000001/00000265.tif/full/200,/0/default.jpg",
                "line": "03",
                "manifest": "https://kotenseki.nijl.ac.jp/biblio/200000993/manifest",
                "name": "200000993 国文学研究資料館所蔵本",
                "page": 780,
                "type": "コマ",
                "vol": 22,
                "work": "源氏物語"
            }
        ],
        "nijl_200010454": [
            {
                "attribution": "国文学研究資料館",
                "canvas": "http://codh.rois.ac.jp/pmjt/iiif/200010454/canvas/00882",
                "curation": 1,
                "image": "http://codh.rois.ac.jp/pmjt/iiif/200010454/200010454_00882.tif/full/200,/0/default.jpg",
                "manifest": "http://codh.rois.ac.jp/pmjt/book/200010454/manifest.json",
                "name": "正徹本（国文学研究資料館所蔵）",
                "page": 883,
                "type": "コマ",
                "vol": 22,
                "work": "源氏物語"
            },
            {
                "attribution": "国文学研究資料館",
                "canvas": "http://codh.rois.ac.jp/pmjt/iiif/200010454/canvas/00883",
                "curation": 1,
                "image": "http://codh.rois.ac.jp/pmjt/iiif/200010454/200010454_00883.tif/full/200,/0/default.jpg",
                "line": "10",
                "manifest": "http://codh.rois.ac.jp/pmjt/book/200010454/manifest.json",
                "name": "正徹本（国文学研究資料館所蔵）",
                "page": 884,
                "type": "コマ",
                "vol": 22,
                "work": "源氏物語"
            }
        ],
        "nijl_200010455": [
            {
                "attribution": "国文学研究資料館",
                "canvas": "https://kotenseki.nijl.ac.jp/biblio/200010455/canvas/795",
                "curation": 1,
                "image": "https://kotenseki.nijl.ac.jp/api/iiif/200010455/v4/NIIP/SA4-0074/SA4-0074-00790.tif/full/200,/0/default.jpg",
                "line": "18",
                "manifest": "https://kotenseki.nijl.ac.jp/biblio/200010455/manifest",
                "name": "国文研 所蔵本3",
                "page": 795,
                "type": "コマ",
                "vol": 22,
                "work": "源氏物語"
            },
            {
                "attribution": "国文学研究資料館",
                "canvas": "https://kotenseki.nijl.ac.jp/biblio/200010455/canvas/796",
                "curation": 1,
                "image": "https://kotenseki.nijl.ac.jp/api/iiif/200010455/v4/NIIP/SA4-0074/SA4-0074-00791.tif/full/200,/0/default.jpg",
                "manifest": "https://kotenseki.nijl.ac.jp/biblio/200010455/manifest",
                "name": "国文研 所蔵本3",
                "page": 796,
                "type": "コマ",
                "vol": 22,
                "work": "源氏物語"
            }
        ],
        "nijl_200016470": [
            {
                "attribution": "国文学研究資料館",
                "canvas": "https://kotenseki.nijl.ac.jp/biblio/200016470/canvas/961",
                "curation": 1,
                "image": "https://kotenseki.nijl.ac.jp/api/iiif/200016470/v4/NIIP/SA4-0098/SA4-0098-00961.tif/full/200,/0/default.jpg",
                "manifest": "https://kotenseki.nijl.ac.jp/biblio/200016470/manifest",
                "name": "国文研 所蔵本2",
                "page": 961,
                "type": "コマ",
                "vol": 22,
                "work": "源氏物語"
            },
            {
                "attribution": "国文学研究資料館",
                "canvas": "https://kotenseki.nijl.ac.jp/biblio/200016470/canvas/962",
                "curation": 1,
                "image": "https://kotenseki.nijl.ac.jp/api/iiif/200016470/v4/NIIP/SA4-0098/SA4-0098-00962.tif/full/200,/0/default.jpg",
                "line": "05",
                "manifest": "https://kotenseki.nijl.ac.jp/biblio/200016470/manifest",
                "name": "国文研 所蔵本2",
                "page": 962,
                "type": "コマ",
                "vol": 22,
                "work": "源氏物語"
            }
        ],
        "nijl_200017428": [
            {
                "attribution": "国文学研究資料館",
                "canvas": "https://kotenseki.nijl.ac.jp/biblio/200017428/canvas/735",
                "curation": 1,
                "image": "https://kotenseki.nijl.ac.jp/api/iiif/200017428/v4/NIIP/SA4-0112/SA4-0112-00735.tif/full/200,/0/default.jpg",
                "line": "16",
                "manifest": "https://kotenseki.nijl.ac.jp/biblio/200017428/manifest",
                "name": "国文研 所蔵本1",
                "page": 735,
                "type": "コマ",
                "vol": 22,
                "work": "源氏物語"
            },
            {
                "attribution": "国文学研究資料館",
                "canvas": "https://kotenseki.nijl.ac.jp/biblio/200017428/canvas/736",
                "curation": 1,
                "image": "https://kotenseki.nijl.ac.jp/api/iiif/200017428/v4/NIIP/SA4-0112/SA4-0112-00736.tif/full/200,/0/default.jpg",
                "manifest": "https://kotenseki.nijl.ac.jp/biblio/200017428/manifest",
                "name": "国文研 所蔵本1",
                "page": 736,
                "type": "コマ",
                "vol": 22,
                "work": "源氏物語"
            }
        ],
        "nijl_200018258": [
            {
                "attribution": "国文研",
                "canvas": "https://kotenseki.nijl.ac.jp/biblio/200018258/canvas/818",
                "image": "https://kotenseki.nijl.ac.jp/api/iiif/200018258/v4/NIKI/096-0020/096-0020-00819.tif/full/200,/0/default.jpg",
                "manifest": "https://raw.githubusercontent.com/nakamura196/genji_curation/master/docs/iiif/nijl/22.json",
                "name": "『湖月抄』鵜飼文庫",
                "page": 818,
                "type": "コマ",
                "work": "玉鬘"
            },
            {
                "attribution": "国文研",
                "canvas": "https://kotenseki.nijl.ac.jp/biblio/200018258/canvas/819",
                "image": "https://kotenseki.nijl.ac.jp/api/iiif/200018258/v4/NIKI/096-0020/096-0020-00820.tif/full/200,/0/default.jpg",
                "manifest": "https://raw.githubusercontent.com/nakamura196/genji_curation/master/docs/iiif/nijl/22.json",
                "name": "『湖月抄』鵜飼文庫",
                "page": 819,
                "type": "コマ",
                "work": "玉鬘"
            }
        ],
        "utokyo": [
            {
                "attribution": "東京大学総合図書館",
                "canvas": "https://iiif.dl.itc.u-tokyo.ac.jp/repo/iiif/26f158f0-357f-8e76-6091-53ed289a2026/canvas/p7",
                "image": "https://iiif.dl.itc.u-tokyo.ac.jp/iiif/genji/TIFF/A00_6587/22/22_0007.tif/full/200,200/0/default.jpg",
                "manifest": "https://nakamura196.github.io/genji/ugm/utokyo/manifest/22.json",
                "name": "東京大学本",
                "page": 7,
                "type": "コマ",
                "work": "玉鬘"
            },
            {
                "attribution": "東京大学総合図書館",
                "canvas": "https://iiif.dl.itc.u-tokyo.ac.jp/repo/iiif/26f158f0-357f-8e76-6091-53ed289a2026/canvas/p8",
                "image": "https://iiif.dl.itc.u-tokyo.ac.jp/iiif/genji/TIFF/A00_6587/22/22_0008.tif/full/200,200/0/default.jpg",
                "manifest": "https://nakamura196.github.io/genji/ugm/utokyo/manifest/22.json",
                "name": "東京大学本",
                "page": 8,
                "type": "コマ",
                "work": "玉鬘"
            }
        ],
        "utokyo_l": [
            {
                "attribution": "東京大学",
                "canvas": "https://kotenseki.nijl.ac.jp/biblio/100018286/canvas/838",
                "curation": 1,
                "image": "https://kotenseki.nijl.ac.jp/api/iiif/100018286/v4/0004/0004-004702/0004-004702-0837.tif/full/200,/0/default.jpg",
                "manifest": "https://kotenseki.nijl.ac.jp/biblio/100018286/manifest",
                "name": "東京大学文学部国文学研究室所蔵本",
                "page": 838,
                "type": "コマ",
                "vol": 22,
                "work": "源氏物語"
            },
            {
                "attribution": "東京大学",
                "canvas": "https://kotenseki.nijl.ac.jp/biblio/100018286/canvas/839",
                "curation": 1,
                "image": "https://kotenseki.nijl.ac.jp/api/iiif/100018286/v4/0004/0004-004702/0004-004702-0838.tif/full/200,/0/default.jpg",
                "line": "02",
                "manifest": "https://kotenseki.nijl.ac.jp/biblio/100018286/manifest",
                "name": "東京大学文学部国文学研究室所蔵本",
                "page": 839,
                "type": "コマ",
                "vol": 22,
                "work": "源氏物語"
            }
        ]
    },
    "type": "ページ",
    "vol_str": "22 玉鬘"
}