{
    "canvas": "https://www.dl.ndl.go.jp/api/iiif/3437686/canvas/77",
    "label": [
        "すさひにてもすきぬへきことをさらにさてすくしてんとおほされす人めをおほ",
        "してへたてをき給よな〱なとはいとしのひかたくくるしきまておほえ給へは",
        "なをたれとなくて二条院にむかへてんもしきこえありてひんなかるへき事なり",
        "ともさるへきにこそは我心なからいとかく人にしむ事はなきをいかなる契にか",
        "はありけんなとおもほしよるいさいと心やすき所にてのとかにきこえんなとか",
        "たらひ給へはなをあやしうかくのたまへとよつかぬ御もてなしなれはものおそ",
        "ろしくこそあれといとわかひていへはけにとほをゑまれ給てけにいつれかきつ",
        "ねなるらんなたゝはかられ給へかしとなつかしけにのたまへは女もいみしくな",
        "ひきてさもありぬへく思たりよになくかたはなる事也ともひたふるにしたかふ",
        "心はいとあはれけなる人とみたまふになをかの頭中将のとこなつうたかはしく",
        "かたりし心さままつおもひいてられ給へとしのふるやうこそはとあなかちにも",
        "とひいてたまはすけしきはみてふとそむきかくるへきこころさまなとはなけれ",
        "はかれ〱にとたえをかむおりこそはさやうにおもひかはることもあらめ心な",
        "からもすこしうつろふ事あらむこそあはれなるへけれとさへおほしけり八月十"
    ],
    "manifest": "https://www.dl.ndl.go.jp/api/iiif/3437686/manifest.json",
    "next": "0116",
    "page": 115,
    "prev": "0114",
    "related": {},
    "type": "ページ",
    "vol_str": "04 夕顔"
}