{
    "canvas": "https://www.dl.ndl.go.jp/api/iiif/3437686/canvas/202",
    "label": [
        "えんなるをおまへなる人々たれはかりならむとつきしろふきこえさせてもかひ",
        "なきものこりにこそむけにくつをれにけれ身のみものうきほとに",
        "　　あひみすてしのふるころのなみたをもなへてのそらのしくれとやみる心の",
        "かよふならはいかになかめの空もものわすれし侍らむなとこまやかになりにけ",
        "りかうやうにおとろかしきこゆるたくひおほかめれとなさけなからすうちかへ",
        "りこち給て御心にはふかうしまさるへし中宮は院の御はてのことにうちつゝき",
        "御八講のいそきをさま〱に心つかひせさせ給けりしも月のついたち比御こき",
        "なるに雪いたうふりたり大将殿より宮にきこえ給",
        "　　別にしけふはくれともみし人にゆきあふほとをいつとたのまんいつこにも",
        "けふはものかなしうおほさるゝほとにて御返あり",
        "　　なからふるほとはうけれとゆきめくりけふはその世にあふ心ちしてことに",
        "つくろひてもあらぬ御かきさまなれとあてにけたかきはおもひなしなるへしす",
        "ちかはりいまめかしうはあらねと人にはことにかゝせ給へりけふはこの御事も",
        "思ひけちてあはれなる雪のしつくにぬれ〱をこなひ給十二月十よ日はかり中"
    ],
    "manifest": "https://www.dl.ndl.go.jp/api/iiif/3437686/manifest.json",
    "page": 364,
    "related": {},
    "type": "ページ",
    "vol_str": "10 賢木"
}