{
    "canvas": "https://www.dl.ndl.go.jp/api/iiif/3437687/canvas/76",
    "label": [
        "ゐてやことはりそいかてかたちとまり給はむわれらもえこそねむしはつましけ",
        "れとをのかみゝにつけたるたよりとも思いてゝとまるましう思へるを人わろく",
        "きゝおはすしもつきはかりになれはゆきあられかちにてほかにはきゆるまもあ",
        "るをあさひゆふひをふせくよもきむくらのかけにふかうつもりてこしのしら山",
        "思ひやらるゝ雪のうちにいているしも人たになくてつれ〱となかめ給ふはか",
        "なきことをきこえなくさめなきみわらひみまきらはしつる人さへなくてよるも",
        "ちりかましき御丁のうちもかたはらさひしくものかなしくおほさるかのとのに",
        "はめつらしひとにいとゝものさはかしき御ありさまにていとやむことなくおほ",
        "されぬところ〱にはわさともえをとつれ給はすましてその人はまたよにやお",
        "はすらむとはかりおほしいつるおりもあれとたつね給ふへき御心さしもいそか",
        "てありふるにとしかはりぬう月はかりに花ちるさとを思いてきこえ給ひてしの",
        "ひてたいのうへに御いとまきこえていて給ふひころふりつるなこりの雨います",
        "こしそゝきておかしきほとに月さしいてたりむかしの御ありきおほしいてられ",
        "てえんなる程のゆふつくよにみちのほとよろつの事おほしいてゝおはするにか"
    ],
    "manifest": "https://www.dl.ndl.go.jp/api/iiif/3437687/manifest.json",
    "next": "0533",
    "page": 532,
    "prev": "0531",
    "related": {
        "nijl_s": [
            {
                "attribution": "aaa",
                "canvas": "http://codh.rois.ac.jp/pmjt/iiif/200010454/canvas/00681",
                "manifest": "http://codh.rois.ac.jp/pmjt/book/200010454/manifest.json",
                "page": 682,
                "type": "コマ",
                "work": "源氏物語"
            },
            {
                "attribution": "aaa",
                "canvas": "http://codh.rois.ac.jp/pmjt/iiif/200010454/canvas/00682",
                "manifest": "http://codh.rois.ac.jp/pmjt/book/200010454/manifest.json",
                "page": 683,
                "type": "コマ",
                "work": "源氏物語"
            }
        ]
    },
    "type": "ページ",
    "vol_str": "15 蓬生"
}