{
    "canvas": "https://www.dl.ndl.go.jp/api/iiif/3437687/canvas/109",
    "label": [
        "ふ御ましりこそわつらはしけれとてうちゑみ給へる御あいきやうところせきま",
        "てこほれぬへしさしより給ひてまことはらうたけなるものをみしかはちきりあ",
        "さくもみえぬをさりとてものめかさむほともはゝかりおほかるに思ひなむわつ",
        "らひぬるおなし心におもひめくらして御心に思さため給へいかゝすへきこゝに",
        "てはくゝみたまひてんやひるのこかよはひにもなりにけるをつみなきさまなる",
        "も思ひすてかたうこそいはけなけなるしもつかたもまきらはさむなとおもふを",
        "めさましとおほさすはひきゆひたまへかしときこえ給ふおもはすにのみとりな",
        "し給ふ御心のへたてをせめてみしらすうらなくやはとてこそいはけなからん御",
        "心にはいとようかなひぬへくなんいかにうつくしきほとにとてすこしうちゑみ",
        "給ひぬちこをわりなうらうたきものにしたまふ御心なれはえていたきかしつか",
        "はやとおほすいかにせましむかへやせましとおほしみたるわたり給こといとか",
        "たしさかのゝみたうの念仏なとまちいてゝ月にふたたひはかりの御ちきりなめ",
        "りとしのわたりにはたちまさりぬへかめるをゝよひなきことゝおもへとも猶い",
        "かゝものおもはしからぬ"
    ],
    "manifest": "https://www.dl.ndl.go.jp/api/iiif/3437687/manifest.json",
    "page": 598,
    "related": {},
    "type": "ページ",
    "vol_str": "18 松風"
}