{
    "canvas": "https://www.dl.ndl.go.jp/api/iiif/3437687/canvas/201",
    "label": [
        "春の日のうらゝにさしてゆくふねはさほのしつくも花そちりけるなとやう",
        "のはかなことゝもを心〱にいひかはしつゝゆくかたもかへらむさともわすれっさあああああｆ",
        "ぬへうわかき人〱の心をうつすにことはりなる水のおもになむくれかゝるほ",
        "とにわうしやうといふかくいとおもしろくきこゆるに心にもあらすつり殿にさ",
        "しよせられておりぬこゝのしつらひいとことそきたるさまになまめかしきに御",
        "方かたのわかき人とものわれおとらしとつくしたるさうすくかたちはなをこき",
        "ませたるにしきにおとらすみえわたる世にめなれすめつらかなるかくともつか",
        "うまつるまひ人なと心ことにえらはせ給て夜にいりぬれはいとあかぬ心ちして",
        "御前のにはにかゝり火ともしてみはしのもとのこけのうへにかく人めしてかん",
        "たちめみこたちもみなをの〱ひきものふきものとりとりにしたまふものゝし",
        "ともことにすくれたるかきりそうてうふきてうへにまちとる御ことゝものしら",
        "へいとはなやかにかきたてゝあなたうとあそひ給ふほといけるかひありとなに",
        "のあやめもしらぬしつのをもみかとのわたりひまなきむまくるまのたちとにま",
        "しりてゑみさかへきゝけりそらのいろものゝねもはるのしらへひゝきはいとこ"
    ],
    "manifest": "https://www.dl.ndl.go.jp/api/iiif/3437687/manifest.json",
    "page": 783,
    "related": {},
    "type": "ページ",
    "vol_str": "24 胡蝶"
}