{
    "canvas": "https://www.dl.ndl.go.jp/api/iiif/3437688/canvas/14",
    "label": [
        "りさまならむゝらさきのうへもひめ君の御あつらへにことつけて物かたりはす",
        "てかたくおほしたりくまのゝものかたりのゑにてあるをいとよくかきたるゑか",
        "なとてこらむすちゐさき女君のなに心もなくてひるねしたまへる所をむかしの",
        "ありさまおほしいてゝ女君はみたまふかゝるわらはとちたにいかにされたりけ",
        "りまろこそなをためしにしつへく心のとけさは人にゝさりけれときこえいて給",
        "へりけにたくひおほからぬ事ともはこのみあつめ給へりけりかしひめ君の御ま",
        "へにてこのよなれたるものかたりなとなよみきかせ給ひそみそか心つきたるも",
        "のゝむすめなとはおかしとにはあらねとかゝる事よにはありけりとみなれ給は",
        "むそゆゝしきやとのたまふもこよなしとたいの御方きゝ給はゝ心をき給ひつへ",
        "くなむうへ心あさけなる人まねともはみるにもかたはらいたくこそうつほのふ",
        "ちはら君のむすめこそいとおもりかにはか〱しき人にてあやまちなかめれと",
        "すくよかにいひいてたる事もしわさも女しき所なかめるそひとやうなめるとの",
        "たまへはうつゝの人もさそあるへかめるひと〱しくたてたるおもむきことに",
        "てよきほとにかまへぬやよしなからぬおやの心とゝめておほしたてたる人のこ"
    ],
    "manifest": "https://www.dl.ndl.go.jp/api/iiif/3437688/manifest.json",
    "next": "0820",
    "page": 819,
    "prev": "0818",
    "related": {},
    "type": "ページ",
    "vol_str": "25 蛍"
}