{
    "canvas": "https://www.dl.ndl.go.jp/api/iiif/3437688/canvas/118",
    "label": [
        "にもほたしなりぬへかりけるさきさき人のうへにみきゝしにも女は心よりほか",
        "にあは〱しく人におとしめらるゝすくせあるなんいとくちおしくかなしきい",
        "つれをも思やうならん御世にはさま〱につけて御心とゝめておほしたつねよ",
        "その中にうしろみなとあるはさるかたにも思ゆつり侍り三宮なむいはけなきよ",
        "はひにてたゝひとりをたのもしき物とならひてうちすてゝむ後の世にたゝよひ",
        "さすらへむこといと〱うしろめたくかなしく侍と御目おしのこひつゝきこえ",
        "しらせさせ給女御にも心うつくしきさまにきこえつけさせ給されと女御の人よ",
        "りはまさりてときめき給ひしにみないとみかはし給しほと御なからひともえう",
        "るはしからさりしかはそのなこりにてけにいまはわさとにくしなとはなくとも",
        "まことに心とゝめて思うしろみむとまてはおほさすもやとそおしはからるゝか",
        "しあさ夕にこの御ことをおほしなけくとしくれ行まゝに御なやみまことにをも",
        "くなりまさらせ給てみすのとにもいてさせ給はす御もののけにて時〻なやませ",
        "給こともありつれといとかくうちはへをやみなきさまにはおはしまさゝりつる",
        "をこのたひは猶かきりなりとおほしめしたり御くらいをさらせ給つれと猶その"
    ],
    "manifest": "https://www.dl.ndl.go.jp/api/iiif/3437688/manifest.json",
    "page": 1027,
    "related": {},
    "type": "ページ",
    "vol_str": "34 若菜 上"
}