{
    "canvas": "https://www.dl.ndl.go.jp/api/iiif/3437688/canvas/146",
    "image": "https://www.dl.ndl.go.jp/api/iiif/3437688/R0000146/pct:50,0,100,100/200,/0/default.jpg",
    "label": [
        "りいけのつゝみすくるほとのよそめはちとせをかねてあそふつるのけころもに",
        "思まかへらる御あそひはしまりて又いとおもしろし御ことゝもは春宮よりそと",
        "ゝのへさせ給ける朱雀院よりわたりまいれるひはきん内よりたまはり給へるさ",
        "うの御ことなとみなむかしおほえたるものゝねともにてめつらしくかきあはせ",
        "給へるになにのをりにもすきにしかたの御ありさまうちわたりなとおほしいて",
        "らる故入道の宮おはせましかはかゝる御賀なとわれこそすゝみつかうまつらま",
        "しかなに事につけてかは心さしもみえたてまつりけんとあかすくちおしくのみ",
        "思いてきこえ給ふ内にもこ宮のおはしまさぬことをなにことにもはえなくさう",
        "〱しくおほさるゝにこの院の御ことをたにれいのあとあるさまのかしこまり",
        "をつくしてもえみせたてまつらぬをよとゝもにあかぬ心地し給もことしは此御",
        "賀にことつけてみゆきなともあるへくおほしをきてけれと世中のわつらひなら",
        "むことさらにせさせ給ましくなんといなひ申給ことたひ〱になりぬれはくち",
        "おしくおほしとまりぬしはすの廿日あまりの程に中宮まかてさせ給てことしの",
        "ゝこりの御いのりにならの京の七大寺に御す行のぬの四千たんこのちかきみや"
    ],
    "manifest": "https://www.dl.ndl.go.jp/api/iiif/3437688/manifest.json",
    "page": 1082,
    "related": {},
    "type": "ページ",
    "vol_str": "34 若菜 上"
}