{
    "canvas": "https://www.dl.ndl.go.jp/api/iiif/3437688/canvas/147",
    "label": [
        "御てかゝせ給へるからのあやのうすたんにしたゑのさまなとおろかならむやは",
        "おもしろき春秋のつくりゑなとよりもこの御屏風のすみつきのかゝやくさまは",
        "めもをよはす思なしさへめてたくなむありけるをきものゝみつしひきものふき",
        "ものなと蔵人所よりたまはり給へり大将の御いきをひもいといかめしくなりた",
        "まひにたれはうちそへてけふのさほういとことなり御むま四十疋左右のむまつ",
        "かさ六衛府の官人かみよりつき〱にひきとゝのふるほとひくれはてぬれいの",
        "万さい楽賀王恩なといふまひけしきはかりまひておとゝのわたり給へるにめつ",
        "らしくもてはやし給へる御あそひにみな人心をいれ給へりひはゝれいの兵部卿",
        "宮なにことにも世にかたき物の上すにおはしていとになしおまへにきんの御こ",
        "とおとゝわこんひき給としころそひ給にける御みゝのきゝなしにやいというに",
        "あはれにおほさるれはきんも御ておさ〱かくしたまはすいみしきねともいつ",
        "むかしの御ものかたりともなといてきていまはたかゝる御なからひにいつかた",
        "につけてもきこえかよひ給へき御むつひなと心よくきこえ給て御みきあまたた",
        "ひまいりて物のおもしろさもとゝこほりなく御ゑいなきともえとゝめ給はす御"
    ],
    "manifest": "https://www.dl.ndl.go.jp/api/iiif/3437688/manifest.json",
    "next": "1086",
    "page": 1085,
    "prev": "1084",
    "related": {},
    "type": "ページ",
    "vol_str": "34 若菜 上"
}