{
    "canvas": "https://www.dl.ndl.go.jp/api/iiif/3437688/canvas/179",
    "label": [
        "ねひまさり給にけりと御らんすはかりよういくわへてみえたてまつりたまへと",
        "事にふれてをしへきこえたまふけにかゝる御うしろみなくてはましていはけな",
        "くおはします御ありさまかくれなからましと人〻もみたてまつる正月廿日許に",
        "なれはそらもおかしきほとに風ぬるくふきておまへのむめもさかりになりゆき",
        "おほかたの花の木ともゝみなけしきはみかすみわたりにけり月たゝは御いそき",
        "ちかく物さはかしからむにかきあはせ給はむ御ことのねもしかくめきて人いひ",
        "なさむをこのころしつかなるほとに心み給へとてしむてんにわたしたてまつり",
        "給ふ御ともにわれも〱と物ゆかしかりてまうのほらまほしかれとこなたにと",
        "をきをはえりとゝめさせ給てすこしねひたれとよしあるかきりえりてさふらは",
        "せ給ふわらはへはかたちすくれたる四人あか色にさくらのかさみうすいろのを",
        "りものゝあこめうきもんのうへのはかまくれなゐのうちたるさまもてなしすく",
        "れたるかきりをめしたり女御の御方にも御しつらひなといとゝあらたまれるこ",
        "ろのくもりなきにをの〱いとましくつくしたるよそおひともあさやかににな",
        "しわらはゝあをいろにすわうのかさみからあやのうへのはかまあこめは山ふき"
    ],
    "manifest": "https://www.dl.ndl.go.jp/api/iiif/3437688/manifest.json",
    "page": 1148,
    "related": {},
    "type": "ページ",
    "vol_str": "35 若菜 下"
}