{
    "canvas": "https://www.dl.ndl.go.jp/api/iiif/3437689/canvas/80",
    "label": [
        "れかたうおもひきこえていまはかくくた〱しき人のかす〱あはれなるをか",
        "たみにみすつへきにやはとたのみきこえけるはかなきひとふしにかうはもてな",
        "し給へくやといみしうあはめうらみまうし給へはなにこともいまはとみあきた",
        "まひにける身なれはいまはたなほるへきにもあらぬをなにかはとてあやしき人",
        "〻はおほしすてすはうれしうこそはあらめときこえたまへりなたらかの御いら",
        "へやいひもていけはたかなかおしきとてしゐてわたり給へともなくてそのよは",
        "ひとりふし給へりあやしう中そらなるころかなとおもひつゝ君たちをまへにふ",
        "せ給てかしこに又いかにおほしみたるらんさまおもひやりきこえやすからぬ心",
        "つくしなれはいかなる人かうやうなることをかしうおほゆらんなとものこりし",
        "ぬへうおほえ給あけぬれは人のみきかむもわか〱しきをかきりとのたまひは",
        "てはさて心みむかしこなる人〻もらうたけにこひきこゆめりしをえりのこし給",
        "へるやうあらむとはみなからおもひすてかたきをともかくももてなしはへりな",
        "むとおとしきこえ給へはすか〱しき御心にてこの君たちをさへやしらぬとこ",
        "ろにゐてわたし給はんとあやふしひめ君をいさたまへかしみたてまつりにかく"
    ],
    "manifest": "https://www.dl.ndl.go.jp/api/iiif/3437689/manifest.json",
    "next": "1373",
    "page": 1372,
    "prev": "1371",
    "related": {},
    "type": "ページ",
    "vol_str": "39 夕霧"
}